factory-stubs/__init__.pyi
factory-stubs/alchemy.pyi
factory-stubs/base.pyi
factory-stubs/builder.pyi
factory-stubs/declarations.pyi
factory-stubs/django.pyi
factory-stubs/enums.pyi
factory-stubs/errors.pyi
factory-stubs/faker.pyi
factory-stubs/fuzzy.pyi
factory-stubs/helpers.pyi
factory-stubs/mogo.pyi
factory-stubs/mongoengine.pyi
factory-stubs/random.pyi
factory-stubs/utils.pyi
types_factory_boy-0.4.0.dist-info/LICENSE
types_factory_boy-0.4.0.dist-info/WHEEL
types_factory_boy-0.4.0.dist-info/METADATA
types_factory_boy-0.4.0.dist-info/RECORD
